select_classifier/__init__.py
select_classifier/select_model.py
ML_Classification_model_selector_Basavaraj100-0.0.3.dist-info/LICENSE
ML_Classification_model_selector_Basavaraj100-0.0.3.dist-info/METADATA
ML_Classification_model_selector_Basavaraj100-0.0.3.dist-info/WHEEL
ML_Classification_model_selector_Basavaraj100-0.0.3.dist-info/top_level.txt
ML_Classification_model_selector_Basavaraj100-0.0.3.dist-info/RECORD
