Metadata-Version: 2.1
Name: ML-Classification-model-selector-Basavaraj100
Version: 0.0.3
Summary: It select best classfication model
Home-page: https://github.com/Basavaraj100/ML_Classification_model_selector
Author: ML_Classification_model_selector
Author-email: benkibijali@gmail.com
License: UNKNOWN
Project-URL: Bug Tracker, https://github.com/Basavaraj100/ML_Classification_model_selector/issues
Platform: UNKNOWN
Classifier: Programming Language :: Python :: 3
Classifier: License :: OSI Approved :: MIT License
Classifier: Operating System :: OS Independent
Requires-Python: >=3.8
License-File: LICENSE
Requires-Dist: pandas
Requires-Dist: numpy
Requires-Dist: matplotlib
Requires-Dist: seaborn
Requires-Dist: sklearn
Requires-Dist: xgboost
Requires-Dist: lightgbm
Requires-Dist: catboost
Requires-Dist: tqdm
Requires-Dist: logging
